README.md
setup.cfg
setup.py
example/__init__.py
example/issueBadge.py
example/listenForBadges.py
rozet/__init__.py
rozet/config.py
rozet/rozet.py
rozet.egg-info/PKG-INFO
rozet.egg-info/SOURCES.txt
rozet.egg-info/dependency_links.txt
rozet.egg-info/requires.txt
rozet.egg-info/top_level.txt
rozet/abis/RozetABI.json
rozet/abis/RozetTokenABI.json
rozet/utils/__init__.py
rozet/utils/crypto.py
rozet/utils/mnemonic.py