Metadata-Version: 1.0
Name: rozet
Version: 1.0.2
Summary: SDK for Rozet Smart Contracts
Home-page: https://github.com/RozetProtocol/rozetPythonSdk
Author: Rozet
Author-email: dave@rozet.io
License: MIT
Platform: UNKNOWN
